baml_core/__init__.py
baml_core/cache_manager/__init__.py
baml_core/cache_manager/abstract_cache_provider.py
baml_core/cache_manager/cache_factory.py
baml_core/cache_manager/cache_manager.py
baml_core/configs/__init__.py
baml_core/configs/retry_policy.py
baml_core/errors/__init__.py
baml_core/errors/llm_exc.py
baml_core/jinja/__init__.py
baml_core/jinja/render_prompt.py
baml_core/jinja/render_prompt_test.py
baml_core/logger.py
baml_core/otel/__init__.py
baml_core/otel/env.py
baml_core/otel/helper.py
baml_core/otel/main.py
baml_core/otel/provider.py
baml_core/otel/py.typed
baml_core/otel/tracer.py
baml_core/otel/tracer.pyi
baml_core/provider_manager/__init__.py
baml_core/provider_manager/llm_manager.py
baml_core/provider_manager/llm_provider_base.py
baml_core/provider_manager/llm_provider_chat.py
baml_core/provider_manager/llm_provider_completion.py
baml_core/provider_manager/llm_provider_factory.py
baml_core/provider_manager/llm_response.py
baml_core/py.typed
baml_core/registrations/__init__.py
baml_core/registrations/caches/__init__.py
baml_core/registrations/caches/gloo_cache.py
baml_core/registrations/providers/__init__.py
baml_core/registrations/providers/anthropic_chat_provider.py
baml_core/registrations/providers/anthropic_provider.py
baml_core/registrations/providers/fallback_provider.py
baml_core/registrations/providers/ollama_chat_provider.py
baml_core/registrations/providers/ollama_completion_provider.py
baml_core/registrations/providers/openai_chat_provider.py
baml_core/registrations/providers/openai_chat_provider_1.py
baml_core/registrations/providers/openai_completion_provider.py
baml_core/registrations/providers/openai_completion_provider_1.py
baml_core/registrations/providers/openai_helper.py
baml_core/registrations/providers/openai_helper_1.py
baml_core/registrations/providers/round_robin_provider.py
baml_core/registrations/providers/test_openai_chat_provider_1.py
baml_core/services/__init__.py
baml_core/services/api.py
baml-0.19.0.dist-info/METADATA
baml-0.19.0.dist-info/WHEEL
baml-0.19.0.dist-info/entry_points.txt
baml-0.19.0.dist-info/RECORD
